redstone_computer_utilities/__init__.py
redstone_computer_utilities/builtins.py
redstone_computer_utilities/cli.py
redstone_computer_utilities/interval.py
redstone_computer_utilities/io.py
redstone_computer_utilities/main.py
redstone_computer_utilities/pos.py
redstone_computer_utilities/py.typed
redstone_computer_utilities/task.py
redstone_computer_utilities/timer.py
redstone_computer_utilities/util.py
redstone_computer_utilities-0.2.1.dist-info/LICENSE
redstone_computer_utilities-0.2.1.dist-info/WHEEL
redstone_computer_utilities-0.2.1.dist-info/METADATA
redstone_computer_utilities-0.2.1.dist-info/RECORD
