Metadata-Version: 2.1
Name: redstone-computer-utilities
Version: 0.2.1
Summary: Lightweight and Modular Redstone Computer Debugging Tools.
Home-page: https://github.com/NKID00/redstone-computer-utilities
License: MPL-2.0
Author: NKID00
Author-email: nkid00@pm.me
Requires-Python: >=3.7.2,<4.0.0
Classifier: License :: OSI Approved
Classifier: Programming Language :: Python :: 3
Classifier: Programming Language :: Python :: 3.8
Classifier: Programming Language :: Python :: 3.9
Classifier: Programming Language :: Python :: 3.10
Requires-Dist: colorama (>=0.4.5,<0.5.0)
Requires-Dist: typing-extensions (>=4.3.0,<5.0.0)
Requires-Dist: uvloop (>=0.17.0,<0.18.0)
